{
  "$schema": "https://raw.githubusercontent.com/QuestPackageManager/QPM.Package/refs/heads/main/qpm.schema.json",
  "sharedDir": "shared",
  "dependenciesDir": "extern",
  "version": "0.1.0",
  "info": {
    "name": "FriendLeaderboard",
    "id": "FriendLeaderboard",
    "version": "0.1.0",
    "url": "https://github.com/evan758321-source/Coolio-thing-vibe-code-3",
    "additionalData": {
      "overrideSoName": "libFriendLeaderboard.so",
      "cmake": true
    }
  },
  "workspace": {
    "ndk": "^27.3.13750724",
    "qmodIncludeDirs": [
      "./build",
      "./extern/libs"
    ],
    "qmodIncludeFiles": [],
    "qmodOutput": "./FriendLeaderboard.qmod"
  },
  "dependencies": [
    {
      "id": "beatsaber-hook",
      "versionRange": "^6.4.2",
      "additionalData": {}
    },
    {
      "id": "bs-cordl",
      "versionRange": "4008.*",
      "additionalData": {}
    },
    {
      "id": "custom-types",
      "versionRange": "^0.18.4",
      "additionalData": {
        "includeQmod": true
      }
    },
    {
      "id": "bsml",
      "versionRange": "^0.4.55",
      "additionalData": {}
    },
    {
      "id": "config-utils",
      "versionRange": "^2.0.3",
      "additionalData": {}
    },
    {
      "id": "scotland2",
      "versionRange": "^0.1.6",
      "additionalData": {
        "includeQmod": false
      }
    },
    {
      "id": "web-utils",
      "versionRange": "^1.1.2",
      "additionalData": {}
    }
  ]
}
